dbbact_calour/__init__.py
dbbact_calour/database_stats.py
dbbact_calour/db_access.py
dbbact_calour/dbannotation.py
dbbact_calour/dbbact.old.py
dbbact_calour/dbbact.py
dbbact_calour/dbbact_calour.old.py
dbbact_calour/dsfdr.py
dbbact_calour/enrichment_gui.py
dbbact_calour/log.cfg
dbbact_calour/term_pairs.py
dbbact_calour/data/chebi.ontology.ids.pickle
dbbact_calour/data/chebi.ontology.pickle
dbbact_calour/data/cl.ontology.ids.pickle
dbbact_calour/data/cl.ontology.pickle
dbbact_calour/data/clo.ontology.ids.pickle
dbbact_calour/data/clo.ontology.pickle
dbbact_calour/data/dbbact.ontology.ids.pickle
dbbact_calour/data/dbbact.ontology.pickle
dbbact_calour/data/doid.ontology.ids.pickle
dbbact_calour/data/doid.ontology.pickle
dbbact_calour/data/efo.ontology.ids.pickle
dbbact_calour/data/efo.ontology.pickle
dbbact_calour/data/envo.ontology.ids.pickle
dbbact_calour/data/envo.ontology.pickle
dbbact_calour/data/foodon.ontology.ids.pickle
dbbact_calour/data/foodon.ontology.pickle
dbbact_calour/data/gaz.ontology.ids.pickle
dbbact_calour/data/gaz.ontology.pickle
dbbact_calour/data/go.ontology.ids.pickle
dbbact_calour/data/go.ontology.pickle
dbbact_calour/data/hp.ontology.ids.pickle
dbbact_calour/data/hp.ontology.pickle
dbbact_calour/data/mondo.ontology.ids.pickle
dbbact_calour/data/mondo.ontology.pickle
dbbact_calour/data/ncbitaxon.ontology.ids.pickle
dbbact_calour/data/ncbitaxon.ontology.pickle
dbbact_calour/data/orphanet.ontology.ids.pickle
dbbact_calour/data/orphanet.ontology.pickle
dbbact_calour/data/other.ontology.ids.pickle
dbbact_calour/data/other.ontology.pickle
dbbact_calour/data/pato.ontology.ids.pickle
dbbact_calour/data/pato.ontology.pickle
dbbact_calour/data/po.ontology.ids.pickle
dbbact_calour/data/po.ontology.pickle
dbbact_calour/data/to.ontology.ids.pickle
dbbact_calour/data/to.ontology.pickle
dbbact_calour/data/uberon.ontology.ids.pickle
dbbact_calour/data/uberon.ontology.pickle
dbbact_calour/data/updated_terms.ontology.ids.pickle
dbbact_calour-1.15.0.dist-info/LICENSE.txt
dbbact_calour-1.15.0.dist-info/METADATA
dbbact_calour-1.15.0.dist-info/WHEEL
dbbact_calour-1.15.0.dist-info/top_level.txt
dbbact_calour-1.15.0.dist-info/RECORD
