Metadata-Version: 2.1
Name: dbbact-calour
Version: 1.15.0
Summary: dbbact-calour is a Calour (https://github.com/biocore/calour) interface for dbBact (dbbact.org)
Home-page: https://github.com/amnona/dbbact-calour
Author: calour development team
Maintainer: calour development team
License: BSD
Keywords: microbiome calour dbbact database analysis bioinformatics
Classifier: Development Status :: 4 - Beta
Classifier: License :: OSI Approved :: BSD License
Classifier: Environment :: Plugins
Classifier: Topic :: Software Development :: Libraries :: Application Frameworks
Classifier: Topic :: Scientific/Engineering
Classifier: Topic :: Scientific/Engineering :: Bio-Informatics
Classifier: Programming Language :: Python
Classifier: Programming Language :: Python :: 3
Classifier: Programming Language :: Python :: 3.6
Classifier: Programming Language :: Python :: 3.7
Classifier: Programming Language :: Python :: 3.8
Classifier: Operating System :: Unix
Classifier: Operating System :: POSIX
Classifier: Operating System :: MacOS :: MacOS X
Classifier: Operating System :: Microsoft :: Windows
Requires-Python: >=3.6
License-File: LICENSE.txt
Requires-Dist: numpy
Requires-Dist: scipy
Requires-Dist: pandas
Requires-Dist: calour
Provides-Extra: coverage
Requires-Dist: coverage ; extra == 'coverage'
Provides-Extra: doc
Requires-Dist: Sphinx (>=1.4) ; extra == 'doc'
Provides-Extra: test
Requires-Dist: nose ; extra == 'test'
Requires-Dist: pep8 ; extra == 'test'
Requires-Dist: flake8 ; extra == 'test'
